pokeapi_sdk/__init__.py
pokeapi_sdk/client.py
pokeapi_sdk/errors.py
pokeapi_sdk-0.1.1.dist-info/METADATA
pokeapi_sdk-0.1.1.dist-info/WHEEL
pokeapi_sdk-0.1.1.dist-info/RECORD
