Metadata-Version: 2.1
Name: pokeapi-sdk
Version: 0.1.1
Summary: 
Author: Your Name
Author-email: you@example.com
Requires-Python: >=3.12,<4.0
Classifier: Programming Language :: Python :: 3
Classifier: Programming Language :: Python :: 3.12
Requires-Dist: requests (>=2.32.3,<3.0.0)
Project-URL: homepage, https://github.com/ThomasN72/pokeapi-sdk
Project-URL: repository, https://github.com/ThomasN72/pokeapi-sdk
